{"cameraMode":{"drawMode":0,"name":"Shaded","section":"Shading Mode"},"sceneLighting":false,"audioPlay":false,"sceneViewState":{"m_AlwaysRefresh":false,"showFog":true,"showSkybox":false,"showFlares":true,"showImageEffects":true,"showParticleSystems":true,"showVisualEffectGraphs":true,"m_FxEnabled":true},"in2DMode":false,"pivot":{"x":-0.19336453080177308,"y":-0.05179288983345032,"z":-0.270943284034729},"rotation":{"x":-0.03348001092672348,"y":0.9197671413421631,"z":-0.08050345629453659,"w":-0.38260617852211},"size":0.3790971338748932,"orthographic":false}